validate_dns_email/__init__.py
validate_dns_email-0.1.0.dist-info/METADATA
validate_dns_email-0.1.0.dist-info/WHEEL
validate_dns_email-0.1.0.dist-info/top_level.txt
validate_dns_email-0.1.0.dist-info/RECORD
