Metadata-Version: 2.1
Name: validate-dns-email
Version: 0.1.0
Summary: Library to validate emails with dns.
Home-page: https://github.com/DeijoseDevelop/validate_dns_email
Author: Deiver Jose Vazquez Moreno
Author-email: estudiandovazmore@gmail.com
License: MIT
Platform: UNKNOWN
Requires-Dist: py3dns (==3.2.1)
